threadpool_with_kill/__init__.py
threadpool_with_kill/pool.py
threadpool_with_kill/pool_final.py
threadpool_with_kill-0.0.7.dist-info/LICENSE
threadpool_with_kill-0.0.7.dist-info/METADATA
threadpool_with_kill-0.0.7.dist-info/WHEEL
threadpool_with_kill-0.0.7.dist-info/top_level.txt
threadpool_with_kill-0.0.7.dist-info/RECORD
