Metadata-Version: 2.1
Name: threadpool-with-kill
Version: 0.0.7
Summary: A thread pool for python
Home-page: https://github.com/chasezcz/ThreadPool
Author: Chengze Zhang
Author-email: 929160190@qq.com
License: UNKNOWN
Platform: UNKNOWN
Classifier: Programming Language :: Python :: 3
Classifier: License :: OSI Approved :: MIT License
License-File: LICENSE
